Workbook

Sheet Tax codes mapping
A1: Id | B1: Tax Code | C1: Avalara_Tax__c | D1: Item Name | E1: Product Category | F1: Tax Code Description
A2: a156g0000032J4aAAE | B2: ST087650 | C2: =VLOOKUP(B2,'Tax Codes'!A$2:D$14,2,FALSE) -> a15WE00000AhUBgYAN | D2: Individual Education Subscription | E2: Education Subscription | F2: Training / Webinar / SaaS Platform / Subscription / No download
A3: a156g0000032LDeAAM | B3: OD020500 | C3: =VLOOKUP(B3,'Tax Codes'!A$2:D$14,2,FALSE) -> a15WE00000AhUBbYAN | D3: ECCHO - Full Member Dues (Prorated for Goldman Sachs) | E3: Membership Dues | F3: Dues (Social, Fraternal, non-entertainment)
A4: a156g0000032MCNAA2 | B4: OD020500 | C4: =VLOOKUP(B4,'Tax Codes'!A$2:D$14,2,FALSE) -> a15WE00000AhUBbYAN | D4: ECCHO Associate Member Quarterly Dues ($20B up to $60B deposit tier) | E4: Membership Dues | F4: Dues (Social, Fraternal, non-entertainment)
A5: a156g0000032PS8AAM | B5: OD020500 | C5: =VLOOKUP(B5,'Tax Codes'!A$2:D$14,2,FALSE) -> a15WE00000AhUBbYAN | D5: ECCHO Participating Member Dues (Prorated for TCF Acquisition) | E5: Membership Dues | F5: Dues (Social, Fraternal, non-entertainment)
A6: a156g0000032k2gAAA | B6: ST087640 | C6: =VLOOKUP(B6,'Tax Codes'!A$2:D$14,2,FALSE) -> a15WE00000AhLmbYAF | D6: Recording: All You Wanted To Know About Check Adjustments | E6: Webinar/Webcast (Pre-recorded) | F6: Training / Webinar Only / SaaS Platform / Pre-recorded, Non-Subscription
A7: a156g0000035yhPAAQ | B7: OD020500 | C7: =VLOOKUP(B7,'Tax Codes'!A$2:D$14,2,FALSE) -> a15WE00000AhUBbYAN | D7: ECCHO - Associate Membership | E7: Membership Dues | F7: Dues (Social, Fraternal, non-entertainment)
A8: a156g0000035yhRAAQ | B8: OD020500 | C8: =VLOOKUP(B8,'Tax Codes'!A$2:D$14,2,FALSE) -> a15WE00000AhUBbYAN | D8: ECCHO - Placeholder Associate Membership Item | E8: Membership Dues | F8: Dues (Social, Fraternal, non-entertainment)
A9: a156g0000035yhSAAQ | B9: OD020500 | C9: =VLOOKUP(B9,'Tax Codes'!A$2:D$14,2,FALSE) -> a15WE00000AhUBbYAN | D9: ECCHO - Placeholder Participating Membership | E9: Membership Dues | F9: Dues (Social, Fraternal, non-entertainment)
A10: a156g0000035yhkAAA | B10: ST087634 | C10: =VLOOKUP(B10,'Tax Codes'!A$2:D$14,2,FALSE) -> a15WE00000AhUBaYAN | D10: What do I do when: Indorsement Claims | E10: Online Training | F10: Online Training
A11: a156g0000035yhpAAA | B11: ST087634 | C11: =VLOOKUP(B11,'Tax Codes'!A$2:D$14,2,FALSE) -> a15WE00000AhUBaYAN | D11: What do I do when: RDC Indemnity 101 | E11: Online Training | F11: Online Training
A12: a156g0000035yhqAAA | B12: ST087634 | C12: =VLOOKUP(B12,'Tax Codes'!A$2:D$14,2,FALSE) -> a15WE00000AhUBaYAN | D12: What do I do when: Unauthorized Remotely Created Check (URCC) | E12: Online Training | F12: Online Training
A13: a156g0000035yhzAAA | B13: ST087634 | C13: =VLOOKUP(B13,'Tax Codes'!A$2:D$14,2,FALSE) -> a15WE00000AhUBaYAN | D13: All About Check: Check Basics: What Every Banker Should Know | E13: Online Training | F13: Online Training
... A122: a15Vy00000T0RqjIAF | B122: OA020500 | C122: =VLOOKUP(B122,'Tax Codes'!A$2:D$14,2,FALSE) -> a15WE00000AhUBZYA3 | D122: Day 3; June 5, 2026 | E122: Conference/Event Registration | F122: Admissions / Events Other Than Entertainment or Amusement

Sheet Tax Codes
A1: Avalara_Tax_Code__c | B1: Id | C1: Name | D1: OrderApi__Description__c
A2: ST087640 | B2: a15WE00000AhLmbYAF | C2: Tax: Pre-recorded Training | D2: Tax: Training / Webinar Only / SaaS Platform / Live, Non-Subscription
A3: OA020500 | B3: a15WE00000AhUBZYA3 | C3: Tax: Admissions / Events | D3: Tax: Admissions / Events Other Than Entertainment or Amusement
A4: ST087634 | B4: a15WE00000AhUBaYAN | C4: Tax: Online Training | D4: Tax: Online Training
A5: OD020500 | B5: a15WE00000AhUBbYAN | C5: Tax: Membership Dues | D5: Tax: Dues (Social, Fraternal, non-entertainment)
A6: SF096370 | B6: a15WE00000AhUBcYAN | C6: Tax: Catering Services | D6: Tax: Catering Services
A7: ST080010 | B7: a15WE00000AhUBdYAN | C7: Tax: Online Skill Assessments | D7: Tax: Online Skill Assessments
A8: P0000000 | B8: a15WE00000AhUBeYAN | C8: Tax: Tangible Personal Property | D8: Tax: Tangible Personal Property (TPP)
A9: SA030000 | B9: a15WE00000AhUBfYAN | C9: Tax: Advertising Services | D9: Tax: Advertising Services - No Transfer of TPP
A10: ST087650 | B10: a15WE00000AhUBgYAN | C10: Tax: Training Subscription | D10: Tax: Training / Webinar / SaaS Platform / Subscription / No download
A11: ST080000 | B11: a15WE00000AhUBhYAN | C11: Tax: Training and Seminar | D11: Tax: Training and Seminar
A12: PB100000 | B12: a15WE00000AhUBiYAN | C12: Tax: Books / Manuals | D12: Tax: Books / Manuals
... A14: OD010000 | B14: a15WE00000AhUBkYAN | C14: Tax: Discounts | D14: Tax: Discounts
